examples/__init__.py
examples/array.py
examples/auto_load_scratch_var.py
pytealext/__init__.py
pytealext/array.py
pytealext/assemble.py
pytealext/auto_load_scratch_var.py
pytealext/cas.py
pytealext/fastexp.py
pytealext/inner_transactions.py
pytealext/lazy.py
pytealext/mul128.py
pytealext/muldiv64.py
pytealext/saturation_math.py
pytealext/serialize.py
pytealext/state.py
pytealext/evaluator/__init__.py
pytealext/evaluator/analytics.py
pytealext/evaluator/evaluator.py
pytealext/evaluator/tools.py
pytealext/evaluator/data/__init__.py
pytealext/evaluator/data/gen_op_costs.py
pytealext/evaluator/data/op_costs.py
tests/__init__.py
tests/all_test.py
tests/analytics_test.py
tests/array_test.py
tests/auto_load_scratch_var_test.py
tests/cas_test.py
tests/evaluator_byte_ops_test.py
tests/evaluator_loop_test.py
tests/evaluator_test.py
tests/evaluator_tools_test.py
tests/fastexp_test.py
tests/inner_txn_test.py
tests/mul128_test.py
tests/muldiv64_test.py
tests/saturation_math_test.py
tests/serialize_test.py
tests/state_test.py
pytealext-3.2.0.dist-info/LICENSE
pytealext-3.2.0.dist-info/METADATA
pytealext-3.2.0.dist-info/WHEEL
pytealext-3.2.0.dist-info/top_level.txt
pytealext-3.2.0.dist-info/RECORD
