Metadata-Version: 2.1
Name: pytealext
Version: 3.2.0
Summary: Extra operations for PyTEAL
Home-page: https://github.com/ulamlabs/pytealext
Author: Łukasz Ptak
Author-email: lukasz@ulam.io
Project-URL: Bug Tracker, https://github.com/ulamlabs/pytealext/issues
Classifier: Programming Language :: Python :: 3
Classifier: License :: OSI Approved :: GNU Lesser General Public License v2 or later (LGPLv2+)
Classifier: Operating System :: OS Independent
Requires-Python: >=3.10
License-File: LICENSE
Requires-Dist: pyteal (<1.0.0,>=0.22.0)
Requires-Dist: py-algorand-sdk (<3.0.0,>=2.0.0)
